README.md
pyproject.toml
setup.py
pwa/__init__.py
pwa/admin.py
pwa/app_settings.py
pwa/apps.py
pwa/models.py
pwa/translation.py
pwa/urls.py
pwa/views.py
pwa/migrations/0001_initial.py
pwa/migrations/__init__.py
pwa/templatetags/__init__.py
pwa/templatetags/pwa.py
rapidbounce_pwa.egg-info/PKG-INFO
rapidbounce_pwa.egg-info/SOURCES.txt
rapidbounce_pwa.egg-info/dependency_links.txt
rapidbounce_pwa.egg-info/requires.txt
rapidbounce_pwa.egg-info/top_level.txt